seven_cloudapp/__init__.py
seven_cloudapp/handlers/__init__.py
seven_cloudapp/handlers/core.py
seven_cloudapp/handlers/seven_base.py
seven_cloudapp/handlers/task_base.py
seven_cloudapp/handlers/top_base.py
seven_cloudapp/handlers/client/__init__.py
seven_cloudapp/handlers/client/act.py
seven_cloudapp/handlers/client/address.py
seven_cloudapp/handlers/client/app.py
seven_cloudapp/handlers/client/exchange.py
seven_cloudapp/handlers/client/goods.py
seven_cloudapp/handlers/client/lottery.py
seven_cloudapp/handlers/client/machine.py
seven_cloudapp/handlers/client/power.py
seven_cloudapp/handlers/client/prize.py
seven_cloudapp/handlers/client/series.py
seven_cloudapp/handlers/client/task.py
seven_cloudapp/handlers/client/theme.py
seven_cloudapp/handlers/client/user.py
seven_cloudapp/handlers/server/__init__.py
seven_cloudapp/handlers/server/act_s.py
seven_cloudapp/handlers/server/app_s.py
seven_cloudapp/handlers/server/base_s.py
seven_cloudapp/handlers/server/exchange_s.py
seven_cloudapp/handlers/server/goods_s.py
seven_cloudapp/handlers/server/machine_s.py
seven_cloudapp/handlers/server/order_s.py
seven_cloudapp/handlers/server/power_s.py
seven_cloudapp/handlers/server/price_s.py
seven_cloudapp/handlers/server/prize_s.py
seven_cloudapp/handlers/server/report_s.py
seven_cloudapp/handlers/server/series_s.py
seven_cloudapp/handlers/server/sms_s.py
seven_cloudapp/handlers/server/task_s.py
seven_cloudapp/handlers/server/theme_s.py
seven_cloudapp/handlers/server/throw_s.py
seven_cloudapp/handlers/server/user_s.py
seven_cloudapp/libs/__init__.py
seven_cloudapp/libs/customize/__init__.py
seven_cloudapp/libs/customize/oss2help.py
seven_cloudapp/libs/customize/seven_helper.py
seven_cloudapp/models/__init__.py
seven_cloudapp/models/behavior_model.py
seven_cloudapp/models/enum.py
seven_cloudapp/models/seven_model.py
seven_cloudapp/models/taobao_model.py
seven_cloudapp/models/throw_model.py
seven_cloudapp/models/db_models/__init__.py
seven_cloudapp/models/db_models/act/__init__.py
seven_cloudapp-1.0.265.dist-info/licenses/LICENSE
seven_cloudapp-1.0.265.dist-info/METADATA
seven_cloudapp-1.0.265.dist-info/WHEEL
seven_cloudapp-1.0.265.dist-info/top_level.txt
seven_cloudapp-1.0.265.dist-info/RECORD
