Metadata-Version: 2.4
Name: seven_cloudapp
Version: 1.0.265
Summary: seven cloudapp
Home-page: http://gitlab.tdtech.gao7.com/TaoBaoCloud/seven_cloudapp.git
Author: seven
Author-email: tech@gao7.com
License: MIT
Classifier: Topic :: Software Development :: Libraries :: Python Modules
Classifier: Programming Language :: Python
Classifier: Programming Language :: Python :: 3.4
Classifier: Programming Language :: Python :: 3.5
Classifier: Programming Language :: Python :: 3.5
Classifier: Programming Language :: Python :: 3.6
Classifier: Programming Language :: Python :: 3.7
Classifier: Programming Language :: Python :: 3.8
Classifier: Programming Language :: Python :: 3.9
Requires-Python: ~=3.4
License-File: LICENSE
Requires-Dist: seven-framework>=1.0.108
Requires-Dist: seven-top>=1.0.18
Requires-Dist: asq>=1.3
Dynamic: author
Dynamic: author-email
Dynamic: classifier
Dynamic: description
Dynamic: description-content-type
Dynamic: home-page
Dynamic: license
Dynamic: license-file
Dynamic: requires-dist
Dynamic: requires-python
Dynamic: summary
